[
 {
   "Time Count(Every 60 seconds)": 0,
   "GT": 0,
   "Fitbit One": 0,
   "Fitbit Flex 2": 0,
   "Fitbit Surge": 0,
   "Fitbit Charge HR": 0,
   "Fitbit Charge 2": 0
 },
 {
   "Time Count(Every 60 seconds)": 1,
   "GT": 2.3,
   "Fitbit One": 0,
   "Fitbit Flex 2": 6,
   "Fitbit Surge": 7,
   "Fitbit Charge HR": 6,
   "Fitbit Charge 2": 6
 },
 {
   "Time Count(Every 60 seconds)": 2,
   "GT": 4.7,
   "Fitbit One": 0,
   "Fitbit Flex 2": 8,
   "Fitbit Surge": 7,
   "Fitbit Charge HR": 8,
   "Fitbit Charge 2": 7
 },
 {
   "Time Count(Every 60 seconds)": 3,
   "GT": 4.9,
   "Fitbit One": 0,
   "Fitbit Flex 2": 0,
   "Fitbit Surge": 8,
   "Fitbit Charge HR": 7,
   "Fitbit Charge 2": 8
 },
 {
   "Time Count(Every 60 seconds)": 4,
   "GT": 4.8,
   "Fitbit One": 0,
   "Fitbit Flex 2": 8,
   "Fitbit Surge": 7,
   "Fitbit Charge HR": 8,
   "Fitbit Charge 2": 7
 },
 {
   "Time Count(Every 60 seconds)": 5,
   "GT": 4.3,
   "Fitbit One": 0,
   "Fitbit Flex 2": 9,
   "Fitbit Surge": 7,
   "Fitbit Charge HR": 7,
   "Fitbit Charge 2": 7
 },
 {
   "Time Count(Every 60 seconds)": 6,
   "GT": 5,
   "Fitbit One": 0,
   "Fitbit Flex 2": 8,
   "Fitbit Surge": 8,
   "Fitbit Charge HR": 8,
   "Fitbit Charge 2": 8
 },
 {
   "Time Count(Every 60 seconds)": 7,
   "GT": 4.7,
   "Fitbit One": 0,
   "Fitbit Flex 2": 9,
   "Fitbit Surge": 7,
   "Fitbit Charge HR": 7,
   "Fitbit Charge 2": 8
 },
 {
   "Time Count(Every 60 seconds)": 8,
   "GT": 5.1,
   "Fitbit One": 0,
   "Fitbit Flex 2": 8,
   "Fitbit Surge": 8,
   "Fitbit Charge HR": 8,
   "Fitbit Charge 2": 7
 },
 {
   "Time Count(Every 60 seconds)": 9,
   "GT": 4.90000000000001,
   "Fitbit One": 0,
   "Fitbit Flex 2": 9,
   "Fitbit Surge": 8,
   "Fitbit Charge HR": 8,
   "Fitbit Charge 2": 8
 },
 {
   "Time Count(Every 60 seconds)": 10,
   "GT": 5.2,
   "Fitbit One": 0,
   "Fitbit Flex 2": 8,
   "Fitbit Surge": 8,
   "Fitbit Charge HR": 8,
   "Fitbit Charge 2": 8
 },
 {
   "Time Count(Every 60 seconds)": 11,
   "GT": 5.5,
   "Fitbit One": 0,
   "Fitbit Flex 2": 9,
   "Fitbit Surge": 8,
   "Fitbit Charge HR": 8,
   "Fitbit Charge 2": 8
 },
 {
   "Time Count(Every 60 seconds)": 12,
   "GT": 5.3,
   "Fitbit One": 0,
   "Fitbit Flex 2": 9,
   "Fitbit Surge": 8,
   "Fitbit Charge HR": 8,
   "Fitbit Charge 2": 0
 },
 {
   "Time Count(Every 60 seconds)": 13,
   "GT": 5.39999999999998,
   "Fitbit One": 0,
   "Fitbit Flex 2": 9,
   "Fitbit Surge": 8,
   "Fitbit Charge HR": 8,
   "Fitbit Charge 2": 9
 },
 {
   "Time Count(Every 60 seconds)": 14,
   "GT": 5.50000000000001,
   "Fitbit One": 0,
   "Fitbit Flex 2": 9,
   "Fitbit Surge": 0,
   "Fitbit Charge HR": 8,
   "Fitbit Charge 2": 9
 },
 {
   "Time Count(Every 60 seconds)": 15,
   "GT": 5.59999999999999,
   "Fitbit One": 0,
   "Fitbit Flex 2": 9,
   "Fitbit Surge": 9,
   "Fitbit Charge HR": 8,
   "Fitbit Charge 2": 9
 },
 {
   "Time Count(Every 60 seconds)": 16,
   "GT": 5.5,
   "Fitbit One": 0,
   "Fitbit Flex 2": 10,
   "Fitbit Surge": 10,
   "Fitbit Charge HR": 8,
   "Fitbit Charge 2": 9
 },
 {
   "Time Count(Every 60 seconds)": 17,
   "GT": 6.5,
   "Fitbit One": 0,
   "Fitbit Flex 2": 9,
   "Fitbit Surge": 11,
   "Fitbit Charge HR": 10,
   "Fitbit Charge 2": 10
 },
 {
   "Time Count(Every 60 seconds)": 18,
   "GT": 7.3,
   "Fitbit One": 0,
   "Fitbit Flex 2": 18,
   "Fitbit Surge": 12,
   "Fitbit Charge HR": 10,
   "Fitbit Charge 2": 11
 },
 {
   "Time Count(Every 60 seconds)": 19,
   "GT": 7.09999999999999,
   "Fitbit One": 0,
   "Fitbit Flex 2": 9,
   "Fitbit Surge": 11,
   "Fitbit Charge HR": 9,
   "Fitbit Charge 2": 12
 },
 {
   "Time Count(Every 60 seconds)": 20,
   "GT": 7.10000000000002,
   "Fitbit One": 0,
   "Fitbit Flex 2": 10,
   "Fitbit Surge": 12,
   "Fitbit Charge HR": 10,
   "Fitbit Charge 2": 11
 },
 {
   "Time Count(Every 60 seconds)": 21,
   "GT": 7.09999999999999,
   "Fitbit One": 0,
   "Fitbit Flex 2": 12,
   "Fitbit Surge": 13,
   "Fitbit Charge HR": 11,
   "Fitbit Charge 2": 13
 },
 {
   "Time Count(Every 60 seconds)": 22,
   "GT": 10,
   "Fitbit One": 0,
   "Fitbit Flex 2": 14,
   "Fitbit Surge": 15,
   "Fitbit Charge HR": 13,
   "Fitbit Charge 2": 15
 },
 {
   "Time Count(Every 60 seconds)": 23,
   "GT": 11.5,
   "Fitbit One": 0,
   "Fitbit Flex 2": 15,
   "Fitbit Surge": 14,
   "Fitbit Charge HR": 13,
   "Fitbit Charge 2": 15
 },
 {
   "Time Count(Every 60 seconds)": 24,
   "GT": 11.6999999999999,
   "Fitbit One": 0,
   "Fitbit Flex 2": 14,
   "Fitbit Surge": 16,
   "Fitbit Charge HR": 14,
   "Fitbit Charge 2": 16
 },
 {
   "Time Count(Every 60 seconds)": 25,
   "GT": 12.2,
   "Fitbit One": 0,
   "Fitbit Flex 2": 15,
   "Fitbit Surge": 17,
   "Fitbit Charge HR": 14,
   "Fitbit Charge 2": 17
 },
 {
   "Time Count(Every 60 seconds)": 26,
   "GT": 12.8,
   "Fitbit One": 0,
   "Fitbit Flex 2": 14,
   "Fitbit Surge": 17,
   "Fitbit Charge HR": 14,
   "Fitbit Charge 2": 16
 },
 {
   "Time Count(Every 60 seconds)": 27,
   "GT": 14.1,
   "Fitbit One": 0,
   "Fitbit Flex 2": 14,
   "Fitbit Surge": 17,
   "Fitbit Charge HR": 15,
   "Fitbit Charge 2": 18
 },
 {
   "Time Count(Every 60 seconds)": 28,
   "GT": 14.6,
   "Fitbit One": 0,
   "Fitbit Flex 2": 14,
   "Fitbit Surge": 18,
   "Fitbit Charge HR": 14,
   "Fitbit Charge 2": 17
 },
 {
   "Time Count(Every 60 seconds)": 29,
   "GT": 15.6,
   "Fitbit One": 0,
   "Fitbit Flex 2": 14,
   "Fitbit Surge": 18,
   "Fitbit Charge HR": 16,
   "Fitbit Charge 2": 18
 },
 {
   "Time Count(Every 60 seconds)": 30,
   "GT": 16.4,
   "Fitbit One": 0,
   "Fitbit Flex 2": 14,
   "Fitbit Surge": 19,
   "Fitbit Charge HR": 15,
   "Fitbit Charge 2": 18
 }
]